repology_client/__init__.py
repology_client/constants.py
repology_client/py.typed
repology_client/types.py
repology_client/utils.py
repology_client/_client/__init__.py
repology_client/_client/tools.py
repology_client/_client/v1.py
repology_client/exceptions/__init__.py
repology_client/exceptions/resolve.py
repology_client-0.6.0.dist-info/METADATA
repology_client-0.6.0.dist-info/WHEEL
repology_client-0.6.0.dist-info/licenses/LICENSES/CC-BY-SA-3.0.txt
repology_client-0.6.0.dist-info/licenses/LICENSES/CC0-1.0.txt
repology_client-0.6.0.dist-info/licenses/LICENSES/EUPL-1.2.txt
repology_client-0.6.0.dist-info/RECORD
