Metadata-Version: 2.4
Name: repology-client
Version: 0.6.0
Summary: Asynchronous wrapper for Repology API
Project-URL: Home, https://repology-client.sysrq.in/
Project-URL: Source, https://git.sysrq.in/python/repology-client
Project-URL: Issues, https://bugs.sysrq.in/enter_bug.cgi?product=Python libraries&component=repology-client
Project-URL: Changelog, https://repology-client.sysrq.in/release-notes.html
Author-email: Anna <cyber@sysrq.in>
License-Expression: EUPL-1.2 AND CC-BY-SA-3.0
License-File: LICENSES/CC-BY-SA-3.0.txt
License-File: LICENSES/CC0-1.0.txt
License-File: LICENSES/EUPL-1.2.txt
Keywords: aiohttp,api,async,repology
Classifier: Development Status :: 4 - Beta
Classifier: Framework :: AsyncIO
Classifier: Intended Audience :: Developers
Classifier: Operating System :: OS Independent
Classifier: Programming Language :: Python
Classifier: Programming Language :: Python :: 3
Classifier: Programming Language :: Python :: 3 :: Only
Classifier: Programming Language :: Python :: Implementation :: CPython
Classifier: Topic :: Software Development :: Libraries :: Python Modules
Classifier: Topic :: System :: Software Distribution
Classifier: Typing :: Typed
Requires-Python: >=3.12
Requires-Dist: aiohttp<4,>=3
Requires-Dist: pydantic-core<3,>=2
Requires-Dist: pydantic<3,>=2
Requires-Dist: yarl
